igenemy/__init__.py
igenemy-0.3.2.dist-info/LICENSE
igenemy-0.3.2.dist-info/METADATA
igenemy-0.3.2.dist-info/WHEEL
igenemy-0.3.2.dist-info/top_level.txt
igenemy-0.3.2.dist-info/RECORD
