Metadata-Version: 2.1
Name: igenemy
Version: 0.3.2
Summary: WebScraping_Instagram
Home-page: https://github.com/kitchun0402/WebScraping_Instagram_igenemy
Author: Kenneth Hau
Author-email: kitchun0402@gmail.com
License: MIT
Platform: UNKNOWN
Requires-Python: >= 3
Requires-Dist: selenium (>=3.141.0)
Requires-Dist: bs4 (>=0.0.1)
Requires-Dist: ipython (>=7.8.0)
Requires-Dist: wget (>=3.2)
